lli_logger/__init__.py
lli_logger/main.py
lli_logger-0.1.4.dist-info/METADATA
lli_logger-0.1.4.dist-info/WHEEL
lli_logger-0.1.4.dist-info/top_level.txt
lli_logger-0.1.4.dist-info/RECORD
