Metadata-Version: 2.4
Name: lli-logger
Version: 0.1.4
Summary: nothing here, sorry(
Author: lliopox
License: MIT
Project-URL: Homepage, https://github.com/LLI0P0X/lli-logger/
Requires-Python: >=3.13
Requires-Dist: loguru==0.7.3
Provides-Extra: aio-tg
Requires-Dist: aiohttp>=3; extra == "aio-tg"
Provides-Extra: sinc-tg
Requires-Dist: requests>=2; extra == "sinc-tg"
